animal_like_train/__init__.py
animal_like_train-0.1.0.dist-info/WHEEL
animal_like_train-0.1.0.dist-info/METADATA
animal_like_train-0.1.0.dist-info/RECORD
