Metadata-Version: 2.1
Name: animal-like-train
Version: 0.1.0
Summary: Mimics the way an animal is trained.
Author: Your Name
Author-email: you@example.com
Requires-Python: >=3.8,<4.0
Classifier: Programming Language :: Python :: 3
Classifier: Programming Language :: Python :: 3.8
